README.rst
_description.org
lh-agpl3-LICENSE.txt
pyproject.toml
setup.py
bin/bifSystemd.cs
bin/exmpl-systemd.cs
bin/seedSystemd.cs
bisos/__init__.py
bisos.debian.egg-info/PKG-INFO
bisos.debian.egg-info/SOURCES.txt
bisos.debian.egg-info/dependency_links.txt
bisos.debian.egg-info/not-zip-safe
bisos.debian.egg-info/requires.txt
bisos.debian.egg-info/top_level.txt
bisos/debian/__init__.py
bisos/debian/bifSystemd.py
bisos/debian/bifSystemd_csu.py
bisos/debian/configFile.py
bisos/debian/systemdSeed.py